smisch.py
src/console/clear_console.py
src/input/anim_input.py
src/input/ask_input.py
src/print/anim_print.py
src/utilities/running_os.py
smisch-1.0.9.dist-info/METADATA
smisch-1.0.9.dist-info/WHEEL
smisch-1.0.9.dist-info/top_level.txt
smisch-1.0.9.dist-info/RECORD
