Metadata-Version: 2.1
Name: smisch
Version: 1.0.9
Summary: Library with addon functions for python.
Author: Smisch
Author-email: smisch@smisch.sk
License: MIT
Keywords: print input
